zealous_wolf/__init__.py
zealous_wolf/metrics.py
zealous_wolf-0.1.dist-info/METADATA
zealous_wolf-0.1.dist-info/WHEEL
zealous_wolf-0.1.dist-info/entry_points.txt
zealous_wolf-0.1.dist-info/top_level.txt
zealous_wolf-0.1.dist-info/RECORD
