Metadata-Version: 2.1
Name: zealous_wolf
Version: 0.1
Summary: A package to calculate net profit and ROI.
Home-page: https://example.com
Author: Semyon Drozdov
Author-email: s.drozdov@edu.centraluniversity.ru
Classifier: Programming Language :: Python :: 3
Classifier: License :: OSI Approved :: MIT License
Classifier: Operating System :: OS Independent
